nomad_camels_driver_keithley_2182a/keithley_2182a.py
nomad_camels_driver_keithley_2182a/keithley_2182a_ophyd.py
nomad_camels_driver_keithley_2182a-0.0.2.dist-info/LICENSE.txt
nomad_camels_driver_keithley_2182a-0.0.2.dist-info/METADATA
nomad_camels_driver_keithley_2182a-0.0.2.dist-info/WHEEL
nomad_camels_driver_keithley_2182a-0.0.2.dist-info/top_level.txt
nomad_camels_driver_keithley_2182a-0.0.2.dist-info/RECORD
